objectscriber/__init__.py
objectscriber/scriber.py
objectscriber-0.0.5.dist-info/LICENSE
objectscriber-0.0.5.dist-info/METADATA
objectscriber-0.0.5.dist-info/WHEEL
objectscriber-0.0.5.dist-info/top_level.txt
objectscriber-0.0.5.dist-info/RECORD
