Metadata-Version: 2.1
Name: objectscriber
Version: 0.0.5
Summary: A simple tool for flexible serialization and desiarelization
Home-page: https://github.com/supersergiy/objectscriber
Author: Sergiy Popovych
Author-email: sergiy.popovich@gmail.com
License: UNKNOWN
Platform: UNKNOWN
Requires-Dist: six
